LICENSE
MANIFEST.in
README.md
RELEASING.md
setup.py
schemaperfect/__init__.py
schemaperfect/codegen.py
schemaperfect/decorator.py
schemaperfect/schemaperfect.py
schemaperfect/utils.py
schemaperfect/version.py
schemaperfect.egg-info/PKG-INFO
schemaperfect.egg-info/SOURCES.txt
schemaperfect.egg-info/dependency_links.txt
schemaperfect.egg-info/requires.txt
schemaperfect.egg-info/top_level.txt
schemaperfect/tests/__init__.py
schemaperfect/tests/test_codegen.py
schemaperfect/tests/test_decorator.py
schemaperfect/tests/test_schemaperfect.py
schemaperfect/tests/test_utils.py