Metadata-Version: 1.2
Name: schemaperfect
Version: 0.5.0
Summary: schemaperfect: generate Python APIs from JSONSchema specifications
Home-page: http://github.com/jwilson8767/schemaperfect
Author: Joshua Wilson
Author-email: jwilson8767@gmail.com
Maintainer: Joshua Wilson
Maintainer-email: jwilson8767@gmail.com
License: BSD
Platform: OS Independent
Requires-Python: >3.6
